Klafybridge-0.1.dist-info/DESCRIPTION.rst
Klafybridge-0.1.dist-info/METADATA
Klafybridge-0.1.dist-info/RECORD
Klafybridge-0.1.dist-info/WHEEL
Klafybridge-0.1.dist-info/entry_points.txt
Klafybridge-0.1.dist-info/metadata.json
Klafybridge-0.1.dist-info/top_level.txt
klafybridge/__init__.py
klafybridge/__main__.py
klafybridge/bridge.py
klafybridge/messages.py
klafybridge/irc_bot/__init__.py
klafybridge/irc_bot/__main__.py
klafybridge/irc_bot/bot.py
klafybridge/tg_bot/__init__.py
klafybridge/tg_bot/__main__.py
klafybridge/tg_bot/bot.py
