Metadata-Version: 2.0
Name: Klafybridge
Version: 0.1
Summary: This is a bridge between Telegram and IRC
Home-page: http://github.com/Klafyvel/Klafybridge
Author: Hugo LEVY-FALK
Author-email: hugo@klafyvel.me
License: UNKNOWN
Project-URL: Source Code, http://github.com/Klafyvel/Klafybridge
Keywords: telegram irc
Platform: UNKNOWN
Classifier: License :: OSI Approved :: MIT License
Requires-Dist: certifi (==2019.11.28)
Requires-Dist: cffi (==1.14.0)
Requires-Dist: click (==7.1.1)
Requires-Dist: cryptography (==2.8)
Requires-Dist: decorator (==4.4.2)
Requires-Dist: future (==0.18.2)
Requires-Dist: irc (==18.0.0)
Requires-Dist: jaraco.classes (==3.1.0)
Requires-Dist: jaraco.collections (==3.0.0)
Requires-Dist: jaraco.functools (==3.0.0)
Requires-Dist: jaraco.logging (==3.0.0)
Requires-Dist: jaraco.stream (==3.0.0)
Requires-Dist: jaraco.text (==3.2.0)
Requires-Dist: more-itertools (==8.2.0)
Requires-Dist: pycparser (==2.20)
Requires-Dist: python-telegram-bot (==12.4.2)
Requires-Dist: pytz (==2019.3)
Requires-Dist: six (==1.14.0)
Requires-Dist: tempora (==3.0.0)
Requires-Dist: toml (==0.10.0)
Requires-Dist: tornado (==6.0.4)
Requires-Dist: importlib-resources (==1.4.0); python_version < "3.7"
Requires-Dist: importlib-metadata (==1.6.0); python_version < "3.8"
Requires-Dist: zipp (==3.1.0); python_version < "3.8"
